axedit/__init__.py
axedit-0.9.9.dist-info/LICENSE
axedit-0.9.9.dist-info/METADATA
axedit-0.9.9.dist-info/WHEEL
axedit-0.9.9.dist-info/entry_points.txt
axedit-0.9.9.dist-info/top_level.txt
axedit-0.9.9.dist-info/RECORD
